{
	"events": [
		{
			"character": "",
			"event_id": "dialogic_010",
			"options": [

			],
			"portrait": "",
			"question": "Go outside?"
		},
		{
			"choice": "Yes.",
			"condition": "",
			"definition": "",
			"event_id": "dialogic_011",
			"value": ""
		},
		{
			"change_scene": "res://_world/Outside.tscn",
			"event_id": "dialogic_041"
		},
		{
			"choice": "No.",
			"condition": "",
			"definition": "",
			"event_id": "dialogic_011",
			"value": ""
		},
		{
			"event_id": "dialogic_013"
		}
	],
	"metadata": {
		"dialogic-version": "1.4.4",
		"file": "timeline-1666021080.json",
		"name": "Door10"
	}
}
